rag-evaluator/__init__.py
rag-evaluator/evaluator.py
rag-evaluator/test.py
rag_evaluator/__init__.py
rag_evaluator/evaluator.py
rag_evaluator/test.py
SEMALEX-1.3.4.dist-info/METADATA
SEMALEX-1.3.4.dist-info/WHEEL
SEMALEX-1.3.4.dist-info/top_level.txt
SEMALEX-1.3.4.dist-info/RECORD
